reqqie/__init__.py
reqqie/__main__.py
reqqie/app.py
reqqie/requirements.py
reqqie-0.0.5.dist-info/LICENSE
reqqie-0.0.5.dist-info/METADATA
reqqie-0.0.5.dist-info/WHEEL
reqqie-0.0.5.dist-info/entry_points.txt
reqqie-0.0.5.dist-info/top_level.txt
reqqie-0.0.5.dist-info/RECORD
