Metadata-Version: 2.1
Name: reqqie
Version: 0.0.5
Summary: Text based Requirements management tool
Home-page: UNKNOWN
Author: Jesper Ribbe
License: UNKNOWN
Platform: UNKNOWN
Classifier: Programming Language :: Python :: 3
Classifier: License :: OSI Approved :: MIT License
Classifier: Operating System :: OS Independent
Requires-Python: >=3.6
Requires-Dist: tdbase (>=0.0.5)
Requires-Dist: typing (>=3.7)
Requires-Dist: pygit2 (>=0.28.2)
Requires-Dist: reportlab (>=3.5.21)
